rld_common_utils/__init__.py
rld_common_utils/helpers.py
rld_common_utils-0.6.1.dist-info/LICENCE
rld_common_utils-0.6.1.dist-info/METADATA
rld_common_utils-0.6.1.dist-info/WHEEL
rld_common_utils-0.6.1.dist-info/top_level.txt
rld_common_utils-0.6.1.dist-info/RECORD
