Metadata-Version: 2.1
Name: rld-common-utils
Version: 0.6.1
Summary: Private package containing shared utilities for rld projects
Classifier: Programming Language :: Python :: 3
Classifier: Operating System :: OS Independent
Requires-Python: >=3.9
License-File: LICENCE
Requires-Dist: urllib3 <2
Provides-Extra: dev
Requires-Dist: ruff ==0.5.5 ; extra == 'dev'
Requires-Dist: codespell ; extra == 'dev'
Requires-Dist: pre-commit ; extra == 'dev'
Requires-Dist: pytest ; extra == 'dev'
Requires-Dist: pytest-cov ; extra == 'dev'
Requires-Dist: python-dotenv ; extra == 'dev'
Provides-Extra: test
Requires-Dist: parameterized ; extra == 'test'
